README.rst
setup.cfg
setup.py
django_tastypie_sepomex.egg-info/PKG-INFO
django_tastypie_sepomex.egg-info/SOURCES.txt
django_tastypie_sepomex.egg-info/dependency_links.txt
django_tastypie_sepomex.egg-info/requires.txt
django_tastypie_sepomex.egg-info/top_level.txt
sepomex/__init__.py
sepomex/models.py
sepomex/settings.py
sepomex/tests.py
sepomex/api/__init__.py
sepomex/api/resources.py
sepomex/management/__init__.py
sepomex/management/commands/__init__.py
sepomex/management/commands/loadmxmunicipalities.py
sepomex/management/commands/loadmxstates.py
sepomex/management/commands/loadsepomex.py
sepomex/migrations/0001_initial.py
sepomex/migrations/0002_auto_20151113_1937.py
sepomex/migrations/0003_auto_20151113_2038.py
sepomex/migrations/0004_auto_20151113_2112.py
sepomex/migrations/0005_auto_20151113_2149.py
sepomex/migrations/0006_auto_20151113_2154.py
sepomex/migrations/__init__.py