Metadata-Version: 1.0
Name: django-tastypie-sepomex
Version: 0.1.0
Summary: Little django application that exposes the sepomex database in a RESTful way.
Home-page: https://github.com/slackmart/tastypie-sepomex
Author: UNKNOWN
Author-email: UNKNOWN
License: MIT
Keywords: sepomex,tastypie,django
Platform: UNKNOWN
